ufl_legacy/__init__.py
ufl_legacy/algebra.py
ufl_legacy/argument.py
ufl_legacy/assertions.py
ufl_legacy/averaging.py
ufl_legacy/cell.py
ufl_legacy/checks.py
ufl_legacy/classes.py
ufl_legacy/coefficient.py
ufl_legacy/compound_expressions.py
ufl_legacy/conditional.py
ufl_legacy/constant.py
ufl_legacy/constantvalue.py
ufl_legacy/differentiation.py
ufl_legacy/domain.py
ufl_legacy/equation.py
ufl_legacy/exprcontainers.py
ufl_legacy/exprequals.py
ufl_legacy/exproperators.py
ufl_legacy/form.py
ufl_legacy/formoperators.py
ufl_legacy/functionspace.py
ufl_legacy/geometry.py
ufl_legacy/index_combination_utils.py
ufl_legacy/indexed.py
ufl_legacy/indexsum.py
ufl_legacy/integral.py
ufl_legacy/log.py
ufl_legacy/mathfunctions.py
ufl_legacy/measure.py
ufl_legacy/measureoperators.py
ufl_legacy/objects.py
ufl_legacy/operators.py
ufl_legacy/permutation.py
ufl_legacy/precedence.py
ufl_legacy/protocols.py
ufl_legacy/referencevalue.py
ufl_legacy/restriction.py
ufl_legacy/sobolevspace.py
ufl_legacy/sorting.py
ufl_legacy/split_functions.py
ufl_legacy/tensoralgebra.py
ufl_legacy/tensors.py
ufl_legacy/variable.py
ufl_legacy/algorithms/__init__.py
ufl_legacy/algorithms/ad.py
ufl_legacy/algorithms/analysis.py
ufl_legacy/algorithms/apply_algebra_lowering.py
ufl_legacy/algorithms/apply_derivatives.py
ufl_legacy/algorithms/apply_function_pullbacks.py
ufl_legacy/algorithms/apply_geometry_lowering.py
ufl_legacy/algorithms/apply_integral_scaling.py
ufl_legacy/algorithms/apply_restrictions.py
ufl_legacy/algorithms/balancing.py
ufl_legacy/algorithms/change_to_reference.py
ufl_legacy/algorithms/check_arities.py
ufl_legacy/algorithms/check_restrictions.py
ufl_legacy/algorithms/checks.py
ufl_legacy/algorithms/comparison_checker.py
ufl_legacy/algorithms/compute_form_data.py
ufl_legacy/algorithms/coordinate_derivative_helpers.py
ufl_legacy/algorithms/domain_analysis.py
ufl_legacy/algorithms/elementtransformations.py
ufl_legacy/algorithms/estimate_degrees.py
ufl_legacy/algorithms/expand_compounds.py
fenics_ufl_legacy-2022.3.0.dist-info/AUTHORS
fenics_ufl_legacy-2022.3.0.dist-info/COPYING
fenics_ufl_legacy-2022.3.0.dist-info/COPYING.LESSER
fenics_ufl_legacy-2022.3.0.dist-info/METADATA
fenics_ufl_legacy-2022.3.0.dist-info/WHEEL
fenics_ufl_legacy-2022.3.0.dist-info/top_level.txt
fenics_ufl_legacy-2022.3.0.dist-info/RECORD
