Metadata-Version: 2.1
Name: fenics-ufl-legacy
Version: 2022.3.0
Summary: Unified Form Language
Home-page: https://github.com/FEniCS/ufl
Author: FEniCS Project Contributors
Maintainer: FEniCS Project Steering Council
License: LGPL-3.0-or-later
Project-URL: Homepage, https://fenicsproject.org
Project-URL: Documentation, https://fenics.readthedocs.io/projects/ufl
Project-URL: Issues, https://github.com/FEniCS/ufl/issues
Project-URL: Funding, https://numfocus.org/donate
Classifier: Development Status :: 5 - Production/Stable
Classifier: Intended Audience :: Developers
Classifier: Intended Audience :: Science/Research
Classifier: License :: OSI Approved :: GNU Lesser General Public License v3 or later (LGPLv3+)
Classifier: Operating System :: POSIX
Classifier: Operating System :: POSIX :: Linux
Classifier: Operating System :: MacOS :: MacOS X
Classifier: Programming Language :: Python
Classifier: Programming Language :: Python :: 3
Classifier: Programming Language :: Python :: 3.7
Classifier: Programming Language :: Python :: 3.8
Classifier: Programming Language :: Python :: 3.9
Classifier: Programming Language :: Python :: 3.10
Classifier: Topic :: Scientific/Engineering :: Mathematics
Classifier: Topic :: Software Development :: Libraries :: Python Modules
Requires-Python: >=3.7
License-File: COPYING
License-File: COPYING.LESSER
License-File: AUTHORS
Requires-Dist: numpy
Provides-Extra: ci
Requires-Dist: coverage ; extra == 'ci'
Requires-Dist: coveralls ; extra == 'ci'
Requires-Dist: pytest-cov ; extra == 'ci'
Requires-Dist: pytest-xdist ; extra == 'ci'
Requires-Dist: fenics-ufl-legacy[docs] ; extra == 'ci'
Requires-Dist: fenics-ufl-legacy[lint] ; extra == 'ci'
Requires-Dist: fenics-ufl-legacy[test] ; extra == 'ci'
Provides-Extra: docs
Requires-Dist: sphinx ; extra == 'docs'
Requires-Dist: sphinx-rtd-theme ; extra == 'docs'
Provides-Extra: lint
Requires-Dist: flake8 ; extra == 'lint'
Requires-Dist: pydocstyle[toml] ; extra == 'lint'
Provides-Extra: test
Requires-Dist: pytest ; extra == 'test'
